questionnaire_mistral/__init__.py
questionnaire_mistral/models/ModelManager.py
questionnaire_mistral/models/__init__.py
questionnaire_mistral/utils/DocumentLoader.py
questionnaire_mistral/utils/__init__.py
questionnaire_mistral-3.1.dist-info/LICENSE
questionnaire_mistral-3.1.dist-info/METADATA
questionnaire_mistral-3.1.dist-info/WHEEL
questionnaire_mistral-3.1.dist-info/dependency_links.txt
questionnaire_mistral-3.1.dist-info/top_level.txt
questionnaire_mistral-3.1.dist-info/RECORD
