Metadata-Version: 2.1
Name: questionnaire_mistral
Version: 3.1
Home-page: https://github.com/skillfi/questionnairemistral
Author: Alex
License: Apache 2.0 License
Classifier: Development Status :: 5 - Production/Stable
Classifier: Intended Audience :: Developers
Classifier: Intended Audience :: Education
Classifier: Intended Audience :: Science/Research
Classifier: License :: OSI Approved :: Apache Software License
Classifier: Operating System :: OS Independent
Classifier: Topic :: Scientific/Engineering :: Artificial Intelligence
Classifier: Programming Language :: Python :: 3
Classifier: Programming Language :: Python :: 3.8
Classifier: Programming Language :: Python :: 3.9
Classifier: Programming Language :: Python :: 3.10
Requires-Python: >=3.8
License-File: LICENSE
Requires-Dist: langchain
Requires-Dist: langchain-community
Requires-Dist: langchain-huggingface
Requires-Dist: playwright
Requires-Dist: html2text
Requires-Dist: sentence-transformers
Requires-Dist: faiss-cpu
Requires-Dist: pandas
Requires-Dist: peft ==0.4.0
Requires-Dist: trl ==0.4.7
Requires-Dist: pypdf
Requires-Dist: bitsandbytes
Requires-Dist: accelerate
Requires-Dist: datasets
Provides-Extra: torch
Requires-Dist: torch ; extra == 'torch'
Requires-Dist: torchvision ; extra == 'torch'
Requires-Dist: torchaudio ; extra == 'torch'
